CHANGELOG.md
LICENSE
README.md
licins.conf
setup.py
doc/licins.1
doc/licenses/Apache-2.0
doc/licenses/BSD-2
doc/licenses/BSD-3
doc/licenses/GFDL-1.2
doc/licenses/GFDL-1.3
doc/licenses/GPL-2
doc/licenses/GPL-3
doc/licenses/LGPL-2
doc/licenses/LGPL-2.1
doc/licenses/LGPL-3
doc/licenses/MIT
licins/__init__.py
licins/core.py
licins.egg-info/PKG-INFO
licins.egg-info/SOURCES.txt
licins.egg-info/dependency_links.txt
licins.egg-info/entry_points.txt
licins.egg-info/top_level.txt
licins/licenses/__init__.py
licins/licenses/apache.py
licins/licenses/bsd2.py
licins/licenses/bsd3.py
licins/licenses/gfdl1-2.py
licins/licenses/gfdl1-3.py
licins/licenses/gpl2.py
licins/licenses/gpl3.py
licins/licenses/lgpl2-1.py
licins/licenses/lgpl2.py
licins/licenses/lgpl3.py
licins/licenses/mit.py
licins/licenses/template.py
licins/licenses/type.py