Metadata-Version: 1.1
Name: licins
Version: 1.1
Summary: Insert commented licenses into source files
Home-page: https://github.com/dogoncouch/licins
Author: Dan Persons
Author-email: dpersonsdev@gmail.com
License: UNKNOWN
Download-URL: https://github.com/dogoncouch/licins/archive/v1.1.tar.gz
Keywords: development,developer-tools,cli,license,license-management,licenses,open-source,open-source-licensing,copyright,software-license
Platform: UNKNOWN
Classifier: Development Status :: 5 - Production/Stable
Classifier: Environment :: Console
Classifier: Intended Audience :: Developers
Classifier: License :: OSI Approved :: MIT License
Classifier: Natural Language :: English
Classifier: Operating System :: POSIX
Classifier: Programming Language :: Python
Classifier: Topic :: Software Development
